bordercrop/LICENSE
bordercrop/__init__.py
bordercrop/__main__.py
bordercrop/bordercrop.py
bordercrop/exceptions.py
bordercrop/utils/__init__.py
bordercrop/utils/annotations.py
bordercrop/utils/validate.py
bordercrop-1.0.0.dist-info/LICENSE
bordercrop-1.0.0.dist-info/METADATA
bordercrop-1.0.0.dist-info/WHEEL
bordercrop-1.0.0.dist-info/entry_points.txt
bordercrop-1.0.0.dist-info/top_level.txt
bordercrop-1.0.0.dist-info/RECORD
