Metadata-Version: 2.1
Name: bordercrop
Version: 1.0.0
Summary: A black borders cropping module
Home-page: https://github.com/Animenosekai/bordercrop
Author: Anime no Sekai
Author-email: niichannomail@gmail.com
License: MIT License
Download-URL: https://github.com/Animenosekai/bordercrop/archive/v1.0.0.tar.gz
Keywords: python,Anime no Sekai,animenosekai,bordercrop,cropping,image,image-processing,image-crop
Platform: UNKNOWN
Classifier: Development Status :: 5 - Production/Stable
Classifier: License :: OSI Approved :: MIT License
Classifier: Programming Language :: Python :: 3
Classifier: Programming Language :: Python :: 3.2
Classifier: Programming Language :: Python :: 3.3
Classifier: Programming Language :: Python :: 3.4
Classifier: Programming Language :: Python :: 3.5
Classifier: Programming Language :: Python :: 3.6
Classifier: Programming Language :: Python :: 3.7
Classifier: Programming Language :: Python :: 3.8
Classifier: Programming Language :: Python :: 3.9
Requires-Python: >=3.2, <4
Requires-Dist: Pillow
Requires-Dist: typing ; python_version < "3.5"
